{
  "schema_version": 1,
  "row_granularity": "one candidate company per row",
  "companies": [
    {
      "company_id": 20433595,
      "company_type": 2,
      "company_name": "PAWAN HANS LIMITED",
      "country_code": "IN",
      "address": "C-14, SECTOR-1 NOIDA GAUTAM BUDDHA",
      "business_scope": "Helicopter support services",
      "trade_total": 4057,
      "trade_match_total": 7,
      "trade_match_percent": 0.17,
      "latest_trade_date_ms": 1734019200000,
      "categories": "胶带",
      "search_terms": "胶带",
      "search_sources": "expansion-search-tape-page-02",
      "product_descriptions": "TAPE, ADHESIVE, SELF-LUBRICARING- P/N.-350A37105720 (AIRCRAFT PARTS FOR NON -SCHEDULED AIRLINES)TAPE, ADHESIVE, SELF-LUBRICARING- P/N.-350A37105720 (AIRCRAF",
      "product_names": "",
      "product_tags": "",
      "product_aliases": "",
      "product_superordinate": "",
      "product_downstream": "",
      "emails": "co.secy@pawanhans.co.in",
      "email_statuses": "co.secy@pawanhans.co.in:0",
      "phones": "",
      "phone_statuses": "",
      "whatsapp": "",
      "websites": "www.pawanhans.co.in",
      "socials": "",
      "contact_source": "UpKuajing customs company contact API",
      "website_research_source": "",
      "website_research_notes": "",
      "website_emails": "",
      "website_phones": "",
      "website_address": "",
      "website_contact_method": "",
      "email_validation_reasons": "",
      "email_validation_source": "UpKuajing customs company contact API (2026-07-17)",
      "email_validation_summary": "无有效邮箱",
      "phone_validation_summary": "无有效电话",
      "research_status": "API无有效联系方式-待补充",
      "market_priority": "常规-全球"
    },
    {
      "company_id": 20433096,
      "company_type": 2,
      "company_name": "SEIREN INDIA PRIVATE LIMITED",
      "country_code": "IN",
      "address": "PLOT NO 19-25 , 32&33 , KADAKOLA INDUSTRIAL AREA, KADAKOLA",
      "business_scope": "Textile and fabric; Viscotecs® system",
      "trade_total": 1514,
      "trade_match_total": 6,
      "trade_match_percent": 0.4,
      "latest_trade_date_ms": 1744300800000,
      "categories": "胶带",
      "search_terms": "胶带",
      "search_sources": "expansion-search-tape-page-02",
      "product_descriptions": "ADHESIVE TAPE AGF-100FR 0.18x19x10m (ACTUAL USER) ADHESIVE TAPE AGF-100FR 0.18x19x10m (ACTUAL USER)",
      "product_names": "Adhesive tape",
      "product_tags": "Adhesive tape",
      "product_aliases": "Sticky tape; Tape; Adhesive strip; Bonding tape; Self - adhesive tape",
      "product_superordinate": "Plastic resin; Adhesive chemicals; Polymer; Solvent; Additives",
      "product_downstream": "Packaging; Crafts; Office use; Automotive repair; Home improvement",
      "emails": "santhosh.s@seiren.co.in",
      "email_statuses": "santhosh.s@seiren.co.in:0",
      "phones": "",
      "phone_statuses": "",
      "whatsapp": "",
      "websites": "www.seiren.com",
      "socials": "https://www.facebook.com/seiren.corporation; https://www.instagram.com/seiren.official; https://twitter.com/seiren_fukui",
      "contact_source": "UpKuajing customs company contact API",
      "website_research_source": "",
      "website_research_notes": "",
      "website_emails": "",
      "website_phones": "",
      "website_address": "",
      "website_contact_method": "",
      "email_validation_reasons": "",
      "email_validation_source": "UpKuajing customs company contact API (2026-07-17)",
      "email_validation_summary": "无有效邮箱",
      "phone_validation_summary": "无有效电话",
      "research_status": "API无有效联系方式-待补充",
      "market_priority": "常规-全球"
    },
    {
      "company_id": 25813060,
      "company_type": 2,
      "company_name": "ALGRAFHER S A S",
      "country_code": "CO",
      "address": "49 38, CALLE 6",
      "business_scope": "",
      "trade_total": 261,
      "trade_match_total": 1,
      "trade_match_percent": 0.38,
      "latest_trade_date_ms": 1733846400000,
      "categories": "遮蔽膜",
      "search_terms": "遮蔽膜",
      "search_sources": "expansion-search-masking-film-page-02",
      "product_descriptions": "DO 032024001708 PEDIDO TRAMITE: IMPO 1331 DECLARACION(1-1) FACTURA: CI240179 FECHA: 2024-10-21 CANT (3) ROLLOS GG CLEAR FILM (BOTH SIDE PE MASKING) 0.250MM X930MM X244M X68KG; PRODUCTO: PEL¿¿CULA TRANSPARENTE GG (ENMASCARAMIENTO DE PE EN AMBOS LADOS), ...",
      "product_names": "GG Clear Film",
      "product_tags": "GG Clear Film; PE; Masking; Film",
      "product_aliases": "Transparent Film; PE Film; Masking Film; Clear Masking Film; GG Film",
      "product_superordinate": "Polyethylene; Plastic Resin; Petrochemicals; Monomers; Additives",
      "product_downstream": "Packaging Industry; Automotive Industry; Electronics Industry; Construction Industry; Printing Industry",
      "emails": "financiera@algrafher.com",
      "email_statuses": "financiera@algrafher.com:0",
      "phones": "5717965050",
      "phone_statuses": "5717965050:状态2/类型0/WhatsApp2",
      "whatsapp": "",
      "websites": "www.algrafher.com",
      "socials": "https://www.linkedin.com/company/algrafhersas",
      "contact_source": "UpKuajing customs company contact API",
      "website_research_source": "",
      "website_research_notes": "",
      "website_emails": "",
      "website_phones": "",
      "website_address": "",
      "website_contact_method": "",
      "email_validation_reasons": "",
      "email_validation_source": "UpKuajing customs company contact API (2026-07-17)",
      "email_validation_summary": "无有效邮箱",
      "phone_validation_summary": "无有效电话",
      "research_status": "API无有效联系方式-待补充",
      "market_priority": "常规-全球"
    }
  ],
  "company_count": 3
}